timeshowxx/__init__.py
timeshowxx/showtime.py
timeshowxx-0.3.0.dist-info/LICENSE
timeshowxx-0.3.0.dist-info/METADATA
timeshowxx-0.3.0.dist-info/WHEEL
timeshowxx-0.3.0.dist-info/top_level.txt
timeshowxx-0.3.0.dist-info/RECORD
