Metadata-Version: 2.1
Name: timeshowxx
Version: 0.3.0
Summary: A brief description of timeshowxx
Author-email: Daniel <daniel251@gmail.com>
Project-URL: Homepage, https://github.com/yourusername/timeshowxx
Project-URL: Issues, https://github.com/yourusername/timeshowxx/issues
Classifier: Programming Language :: Python :: 3
Classifier: License :: OSI Approved :: MIT License
Classifier: Operating System :: OS Independent
Requires-Python: >=3.8
License-File: LICENSE
